gentoo_update/__init__.py
gentoo_update/_version.py
gentoo_update/gentoo_update.py
gentoo_update/notifier.py
gentoo_update/parser.py
gentoo_update/parser_package.py
gentoo_update/report_objects.py
gentoo_update/reporter.py
gentoo_update/shell_runner.py
gentoo_update/scripts/updater.sh
gentoo_update-0.2.4.dist-info/LICENSE
gentoo_update-0.2.4.dist-info/METADATA
gentoo_update-0.2.4.dist-info/WHEEL
gentoo_update-0.2.4.dist-info/entry_points.txt
gentoo_update-0.2.4.dist-info/top_level.txt
gentoo_update-0.2.4.dist-info/RECORD
