Metadata-Version: 2.1
Name: gentoo-update
Version: 0.2.4
Summary: Gentoo Linux updater
Home-page: https://github.com/Lab-Brat/gentoo_update
Author: Lab-Brat
Author-email: labbrat_social@pm.me
License: MIT
Classifier: License :: OSI Approved :: MIT License
Classifier: Programming Language :: Python :: 3.10
Classifier: Operating System :: POSIX :: Linux
Requires-Python: >=3.10
License-File: LICENSE
